Metadata-Version: 2.1
Name: lockfolder
Version: 1.0.2
Summary: check-bid-check into a lock folder, to obtain a lock
Home-page: https://github.com/LionKimbro/lockfolder
Author: Lion Kimbro
Author-email: Lion Kimbro <lionkimbro@gmail.com>
Project-URL: Homepage, https://github.com/LionKimbro/lockfolder
Project-URL: Bug Tracker, https://github.com/LionKimbro/lockfolder/issues
Keywords: mutex,lock,locking,guid
Classifier: Programming Language :: Python :: 3
Classifier: License :: OSI Approved :: MIT License
Classifier: Operating System :: OS Independent
Requires-Python: >=3.7
License-File: LICENSE
